pukpuk/__init__.py
pukpuk/base.py
pukpuk/cli.py
pukpuk/logs.py
pukpuk/mods.py
pukpuk/version.py
pukpuk-3.3.0.dist-info/METADATA
pukpuk-3.3.0.dist-info/WHEEL
pukpuk-3.3.0.dist-info/entry_points.txt
pukpuk-3.3.0.dist-info/top_level.txt
pukpuk-3.3.0.dist-info/RECORD
