Metadata-Version: 2.2
Name: pukpuk
Version: 3.3.0
Summary: HTTP discovery toolkit
Author-email: tasooshi <tasooshi@pm.me>
License: MIT License
Project-URL: Source, https://github.com/tasooshi/pukpuk/
Keywords: HTTP,discovery,scanning
Classifier: Development Status :: 5 - Production/Stable
Classifier: Topic :: Utilities
Classifier: License :: OSI Approved :: MIT License
Classifier: Programming Language :: Python :: 3.12
Classifier: Programming Language :: Python :: 3.13
Requires-Python: >=3.12
Requires-Dist: dnspython>=2.7.0
Requires-Dist: netaddr>=1.3.0
Requires-Dist: pillow>=11.1.0
Requires-Dist: pyopenssl>=25.0.0
Requires-Dist: requests>=2.32.3
